pensimpy/__init__.py
pensimpy/_version.py
pensimpy/constants.py
pensimpy/peni_env_setup.py
pensimpy/utils.py
pensimpy/data/__init__.py
pensimpy/data/batch_data.py
pensimpy/data/channel.py
pensimpy/data/constants.py
pensimpy/data/ctrl_flags.py
pensimpy/examples/__init__.py
pensimpy/examples/batch_generation.py
pensimpy/examples/recipe.py
pensimpy/examples/reinforcement_learning_boilerplate.py
pensimpy/ode/__init__.py
pensimpy/ode/indpensim_ode_py.py
pensimpy-1.2.5.dist-info/LICENSE
pensimpy-1.2.5.dist-info/METADATA
pensimpy-1.2.5.dist-info/WHEEL
pensimpy-1.2.5.dist-info/top_level.txt
pensimpy-1.2.5.dist-info/RECORD
