Metadata-Version: 2.1
Name: pensimpy
Version: 1.2.5
Summary: The Python implementation of IndPenSim
Home-page: https://github.com/Quarticai/PenSimPy.git
Author: Quartic
Author-email: 
License: UNKNOWN
Platform: UNKNOWN
Classifier: Programming Language :: Python :: 3
Classifier: License :: OSI Approved :: MIT License
Classifier: Operating System :: OS Independent
Requires-Python: >=3.8
Requires-Dist: numpy (==1.18.2)
Requires-Dist: pandas (==1.0.3)
Requires-Dist: scipy (==1.4.1)
Requires-Dist: fastodeint (==0.0.1)
